rival_regions_calc/__init__.py
rival_regions_calc/building.py
rival_regions_calc/construction_costs.py
rival_regions_calc/deep_exploration.py
rival_regions_calc/item.py
rival_regions_calc/resource_coefficient.py
rival_regions_calc/value.py
rival_regions_calc/work_production.py
rival_regions_calc-1.1.2.dist-info/LICENSE
rival_regions_calc-1.1.2.dist-info/METADATA
rival_regions_calc-1.1.2.dist-info/WHEEL
rival_regions_calc-1.1.2.dist-info/top_level.txt
rival_regions_calc-1.1.2.dist-info/RECORD
