Metadata-Version: 2.1
Name: rival-regions-calc
Version: 1.1.2
Summary: Rival Regions calculations
Home-page: https://github.com/joostsijm/rival_regions_calc
Author: Joost Sijm
Author-email: joostsijm@gmail.com
License: UNKNOWN
Platform: UNKNOWN
Classifier: Programming Language :: Python :: 3
Classifier: License :: OSI Approved :: Apache Software License
Classifier: Operating System :: OS Independent
